{
  "schema_version": 2,
  "run": {
    "run_id": "run_full_2026年5月12日_20时01分04秒_96689add",
    "relative_path": "C6对称结构\\六臂星\\results\\所有臂同步缩放扰动\\旧文件\\full\\不收敛\\run_full_2026年5月12日_20时01分04秒",
    "group": "C6",
    "mother_structure": "六臂星",
    "perturbation": "所有臂同步缩放扰动",
    "reduction_path": "C6 -> 待识别",
    "status": "done",
    "risk": "medium",
    "risk_level": "medium",
    "risk_label": "中",
    "mode": "full",
    "spectrum_count": 10,
    "spectra_count": 10,
    "sample_count": 9,
    "has_T": true,
    "has_R": false,
    "has_A": false,
    "has_field": false,
    "has_phase": false,
    "has_poynting": false,
    "best_score": 4.635887189801226,
    "score": 4.635887189801226,
    "lambda0_nm": 1507.0921985815603,
    "Q": 5.01621290057215,
    "q": 5.01621290057215,
    "FWHM_nm": 300.44422524603397,
    "fwhm_nm": 300.44422524603397,
    "max_t": 0.9241807251310588,
    "modified_at": "2026-05-12T20:01:53",
    "mtime": 1778587313.4080186,
    "fingerprint": {
      "mtime_max": 1778587673.0265357,
      "total_size": 258840814,
      "file_count": 31,
      "dir_count": 6,
      "fingerprint": "1778587673.0265357-258840814-31-6"
    },
    "last_indexed_at": "2026-05-20T14:34:08",
    "source_job_id": null,
    "missing_evidence": [
      "R",
      "A",
      "Field",
      "Phase",
      "Poynting"
    ],
    "quality_flags": [
      "缺 R",
      "缺 A",
      "缺 Field",
      "缺 Phase",
      "缺 Poynting"
    ],
    "evidence": {
      "T": true,
      "R": false,
      "A": false,
      "Field": false,
      "Phase": false,
      "Poynting": false
    },
    "quality_flag_records": [
      {
        "run_id": "run_full_2026年5月12日_20时01分04秒_96689add",
        "sample_id": null,
        "flag": "缺 R",
        "severity": "warning",
        "detail": "缺少 R 补证数据",
        "suggestion": "进入补做实验生成任务包"
      },
      {
        "run_id": "run_full_2026年5月12日_20时01分04秒_96689add",
        "sample_id": null,
        "flag": "缺 A",
        "severity": "warning",
        "detail": "缺少 A 补证数据",
        "suggestion": "进入补做实验生成任务包"
      },
      {
        "run_id": "run_full_2026年5月12日_20时01分04秒_96689add",
        "sample_id": null,
        "flag": "缺 Field",
        "severity": "warning",
        "detail": "缺少 Field 补证数据",
        "suggestion": "进入补做实验生成任务包"
      },
      {
        "run_id": "run_full_2026年5月12日_20时01分04秒_96689add",
        "sample_id": null,
        "flag": "缺 Phase",
        "severity": "warning",
        "detail": "缺少 Phase 补证数据",
        "suggestion": "进入补做实验生成任务包"
      },
      {
        "run_id": "run_full_2026年5月12日_20时01分04秒_96689add",
        "sample_id": null,
        "flag": "缺 Poynting",
        "severity": "warning",
        "detail": "缺少 Poynting 补证数据",
        "suggestion": "进入补做实验生成任务包"
      }
    ]
  },
  "samples": [
    {
      "sample_id": "0",
      "delta": "5.000000000000001e-07",
      "lambda0_nm": 1507.0921985815603,
      "score": 4.635887189801226,
      "missing_evidence": [
        "R",
        "A",
        "Field",
        "Phase",
        "Poynting"
      ],
      "source_fsp": "C6对称结构\\六臂星\\results\\所有臂同步缩放扰动\\旧文件\\full\\不收敛\\run_full_2026年5月12日_20时01分04秒\\01_fsp\\0000_all_arm_length_arm_length_500.000nm.fsp"
    },
    {
      "sample_id": "1",
      "delta": "5.250000000000001e-07",
      "lambda0_nm": 1507.0921985815603,
      "score": 4.635887189801226,
      "missing_evidence": [
        "R",
        "A",
        "Field",
        "Phase",
        "Poynting"
      ],
      "source_fsp": "C6对称结构\\六臂星\\results\\所有臂同步缩放扰动\\旧文件\\full\\不收敛\\run_full_2026年5月12日_20时01分04秒\\01_fsp\\0001_all_arm_length_arm_length_525.000nm.fsp"
    },
    {
      "sample_id": "2",
      "delta": "5.5e-07",
      "lambda0_nm": 1507.0921985815603,
      "score": 4.635887189801226,
      "missing_evidence": [
        "R",
        "A",
        "Field",
        "Phase",
        "Poynting"
      ],
      "source_fsp": "C6对称结构\\六臂星\\results\\所有臂同步缩放扰动\\旧文件\\full\\不收敛\\run_full_2026年5月12日_20时01分04秒\\01_fsp\\0002_all_arm_length_arm_length_550.000nm.fsp"
    },
    {
      "sample_id": "3",
      "delta": "5.75e-07",
      "lambda0_nm": 1507.0921985815603,
      "score": 4.635887189801226,
      "missing_evidence": [
        "R",
        "A",
        "Field",
        "Phase",
        "Poynting"
      ],
      "source_fsp": "C6对称结构\\六臂星\\results\\所有臂同步缩放扰动\\旧文件\\full\\不收敛\\run_full_2026年5月12日_20时01分04秒\\01_fsp\\0003_all_arm_length_arm_length_575.000nm.fsp"
    },
    {
      "sample_id": "4",
      "delta": "6e-07",
      "lambda0_nm": 1507.0921985815603,
      "score": 4.635887189801226,
      "missing_evidence": [
        "R",
        "A",
        "Field",
        "Phase",
        "Poynting"
      ],
      "source_fsp": "C6对称结构\\六臂星\\results\\所有臂同步缩放扰动\\旧文件\\full\\不收敛\\run_full_2026年5月12日_20时01分04秒\\01_fsp\\0004_all_arm_length_arm_length_600.000nm.fsp"
    },
    {
      "sample_id": "5",
      "delta": "6.249999999999999e-07",
      "lambda0_nm": 1507.0921985815603,
      "score": 4.635887189801226,
      "missing_evidence": [
        "R",
        "A",
        "Field",
        "Phase",
        "Poynting"
      ],
      "source_fsp": "C6对称结构\\六臂星\\results\\所有臂同步缩放扰动\\旧文件\\full\\不收敛\\run_full_2026年5月12日_20时01分04秒\\01_fsp\\0005_all_arm_length_arm_length_625.000nm.fsp"
    },
    {
      "sample_id": "6",
      "delta": "6.499999999999999e-07",
      "lambda0_nm": 1507.0921985815603,
      "score": 4.635887189801226,
      "missing_evidence": [
        "R",
        "A",
        "Field",
        "Phase",
        "Poynting"
      ],
      "source_fsp": "C6对称结构\\六臂星\\results\\所有臂同步缩放扰动\\旧文件\\full\\不收敛\\run_full_2026年5月12日_20时01分04秒\\01_fsp\\0006_all_arm_length_arm_length_650.000nm.fsp"
    },
    {
      "sample_id": "7",
      "delta": "6.749999999999999e-07",
      "lambda0_nm": 1507.0921985815603,
      "score": 4.635887189801226,
      "missing_evidence": [
        "R",
        "A",
        "Field",
        "Phase",
        "Poynting"
      ],
      "source_fsp": "C6对称结构\\六臂星\\results\\所有臂同步缩放扰动\\旧文件\\full\\不收敛\\run_full_2026年5月12日_20时01分04秒\\01_fsp\\0007_all_arm_length_arm_length_675.000nm.fsp"
    },
    {
      "sample_id": "8",
      "delta": "6.999999999999999e-07",
      "lambda0_nm": 1507.0921985815603,
      "score": 4.635887189801226,
      "missing_evidence": [
        "R",
        "A",
        "Field",
        "Phase",
        "Poynting"
      ],
      "source_fsp": "C6对称结构\\六臂星\\results\\所有臂同步缩放扰动\\旧文件\\full\\不收敛\\run_full_2026年5月12日_20时01分04秒\\01_fsp\\0008_all_arm_length_arm_length_700.000nm.fsp"
    }
  ],
  "files": [
    {
      "relative_path": "C6对称结构\\六臂星\\results\\所有臂同步缩放扰动\\旧文件\\full\\不收敛\\run_full_2026年5月12日_20时01分04秒\\00_scan_plan\\scan_points.csv",
      "name": "scan_points.csv",
      "extension": "csv",
      "kind": "csv",
      "size": 737,
      "mtime": 1778587269.346666,
      "mtime_iso": "2026-05-12T20:01:09"
    },
    {
      "relative_path": "C6对称结构\\六臂星\\results\\所有臂同步缩放扰动\\旧文件\\full\\不收敛\\run_full_2026年5月12日_20时01分04秒\\manifest.csv",
      "name": "manifest.csv",
      "extension": "csv",
      "kind": "csv",
      "size": 7134,
      "mtime": 1778587673.0265357,
      "mtime_iso": "2026-05-12T20:07:53"
    },
    {
      "relative_path": "C6对称结构\\六臂星\\results\\所有臂同步缩放扰动\\旧文件\\full\\不收敛\\run_full_2026年5月12日_20时01分04秒\\01_fsp\\0000_all_arm_length_arm_length_500.000nm.fsp",
      "name": "0000_all_arm_length_arm_length_500.000nm.fsp",
      "extension": "fsp",
      "kind": "fsp",
      "size": 25803257,
      "mtime": 1778587312.1770828,
      "mtime_iso": "2026-05-12T20:01:52"
    },
    {
      "relative_path": "C6对称结构\\六臂星\\results\\所有臂同步缩放扰动\\旧文件\\full\\不收敛\\run_full_2026年5月12日_20时01分04秒\\01_fsp\\0001_all_arm_length_arm_length_525.000nm.fsp",
      "name": "0001_all_arm_length_arm_length_525.000nm.fsp",
      "extension": "fsp",
      "kind": "fsp",
      "size": 25803257,
      "mtime": 1778587356.629874,
      "mtime_iso": "2026-05-12T20:02:36"
    },
    {
      "relative_path": "C6对称结构\\六臂星\\results\\所有臂同步缩放扰动\\旧文件\\full\\不收敛\\run_full_2026年5月12日_20时01分04秒\\01_fsp\\0002_all_arm_length_arm_length_550.000nm.fsp",
      "name": "0002_all_arm_length_arm_length_550.000nm.fsp",
      "extension": "fsp",
      "kind": "fsp",
      "size": 25803257,
      "mtime": 1778587401.3353667,
      "mtime_iso": "2026-05-12T20:03:21"
    },
    {
      "relative_path": "C6对称结构\\六臂星\\results\\所有臂同步缩放扰动\\旧文件\\full\\不收敛\\run_full_2026年5月12日_20时01分04秒\\01_fsp\\0003_all_arm_length_arm_length_575.000nm.fsp",
      "name": "0003_all_arm_length_arm_length_575.000nm.fsp",
      "extension": "fsp",
      "kind": "fsp",
      "size": 25803257,
      "mtime": 1778587444.815349,
      "mtime_iso": "2026-05-12T20:04:04"
    },
    {
      "relative_path": "C6对称结构\\六臂星\\results\\所有臂同步缩放扰动\\旧文件\\full\\不收敛\\run_full_2026年5月12日_20时01分04秒\\01_fsp\\0004_all_arm_length_arm_length_600.000nm.fsp",
      "name": "0004_all_arm_length_arm_length_600.000nm.fsp",
      "extension": "fsp",
      "kind": "fsp",
      "size": 25803257,
      "mtime": 1778587488.723777,
      "mtime_iso": "2026-05-12T20:04:48"
    },
    {
      "relative_path": "C6对称结构\\六臂星\\results\\所有臂同步缩放扰动\\旧文件\\full\\不收敛\\run_full_2026年5月12日_20时01分04秒\\01_fsp\\0005_all_arm_length_arm_length_625.000nm.fsp",
      "name": "0005_all_arm_length_arm_length_625.000nm.fsp",
      "extension": "fsp",
      "kind": "fsp",
      "size": 25803257,
      "mtime": 1778587534.5799167,
      "mtime_iso": "2026-05-12T20:05:34"
    },
    {
      "relative_path": "C6对称结构\\六臂星\\results\\所有臂同步缩放扰动\\旧文件\\full\\不收敛\\run_full_2026年5月12日_20时01分04秒\\01_fsp\\0006_all_arm_length_arm_length_650.000nm.fsp",
      "name": "0006_all_arm_length_arm_length_650.000nm.fsp",
      "extension": "fsp",
      "kind": "fsp",
      "size": 25803257,
      "mtime": 1778587580.03598,
      "mtime_iso": "2026-05-12T20:06:20"
    },
    {
      "relative_path": "C6对称结构\\六臂星\\results\\所有臂同步缩放扰动\\旧文件\\full\\不收敛\\run_full_2026年5月12日_20时01分04秒\\01_fsp\\0007_all_arm_length_arm_length_675.000nm.fsp",
      "name": "0007_all_arm_length_arm_length_675.000nm.fsp",
      "extension": "fsp",
      "kind": "fsp",
      "size": 25803257,
      "mtime": 1778587624.98163,
      "mtime_iso": "2026-05-12T20:07:04"
    },
    {
      "relative_path": "C6对称结构\\六臂星\\results\\所有臂同步缩放扰动\\旧文件\\full\\不收敛\\run_full_2026年5月12日_20时01分04秒\\01_fsp\\0008_all_arm_length_arm_length_700.000nm.fsp",
      "name": "0008_all_arm_length_arm_length_700.000nm.fsp",
      "extension": "fsp",
      "kind": "fsp",
      "size": 25803209,
      "mtime": 1778587672.709924,
      "mtime_iso": "2026-05-12T20:07:52"
    },
    {
      "relative_path": "C6对称结构\\六臂星\\results\\所有臂同步缩放扰动\\旧文件\\full\\不收敛\\run_full_2026年5月12日_20时01分04秒\\05_work_fsp\\master_template.fsp",
      "name": "master_template.fsp",
      "extension": "fsp",
      "kind": "fsp",
      "size": 25803401,
      "mtime": 1777217205.5324945,
      "mtime_iso": "2026-04-26T23:26:45"
    },
    {
      "relative_path": "C6对称结构\\六臂星\\results\\所有臂同步缩放扰动\\旧文件\\full\\不收敛\\run_full_2026年5月12日_20时01分04秒\\03_transmission_abs2_png\\0000_all_arm_length_arm_length_500.000nm_transmission_abs2.png",
      "name": "0000_all_arm_length_arm_length_500.000nm_transmission_abs2.png",
      "extension": "png",
      "kind": "image",
      "size": 62399,
      "mtime": 1778587313.4071553,
      "mtime_iso": "2026-05-12T20:01:53"
    },
    {
      "relative_path": "C6对称结构\\六臂星\\results\\所有臂同步缩放扰动\\旧文件\\full\\不收敛\\run_full_2026年5月12日_20时01分04秒\\03_transmission_abs2_png\\0001_all_arm_length_arm_length_525.000nm_transmission_abs2.png",
      "name": "0001_all_arm_length_arm_length_525.000nm_transmission_abs2.png",
      "extension": "png",
      "kind": "image",
      "size": 62249,
      "mtime": 1778587356.9213204,
      "mtime_iso": "2026-05-12T20:02:36"
    },
    {
      "relative_path": "C6对称结构\\六臂星\\results\\所有臂同步缩放扰动\\旧文件\\full\\不收敛\\run_full_2026年5月12日_20时01分04秒\\03_transmission_abs2_png\\0002_all_arm_length_arm_length_550.000nm_transmission_abs2.png",
      "name": "0002_all_arm_length_arm_length_550.000nm_transmission_abs2.png",
      "extension": "png",
      "kind": "image",
      "size": 61696,
      "mtime": 1778587401.6439502,
      "mtime_iso": "2026-05-12T20:03:21"
    },
    {
      "relative_path": "C6对称结构\\六臂星\\results\\所有臂同步缩放扰动\\旧文件\\full\\不收敛\\run_full_2026年5月12日_20时01分04秒\\03_transmission_abs2_png\\0003_all_arm_length_arm_length_575.000nm_transmission_abs2.png",
      "name": "0003_all_arm_length_arm_length_575.000nm_transmission_abs2.png",
      "extension": "png",
      "kind": "image",
      "size": 61175,
      "mtime": 1778587445.183988,
      "mtime_iso": "2026-05-12T20:04:05"
    },
    {
      "relative_path": "C6对称结构\\六臂星\\results\\所有臂同步缩放扰动\\旧文件\\full\\不收敛\\run_full_2026年5月12日_20时01分04秒\\03_transmission_abs2_png\\0004_all_arm_length_arm_length_600.000nm_transmission_abs2.png",
      "name": "0004_all_arm_length_arm_length_600.000nm_transmission_abs2.png",
      "extension": "png",
      "kind": "image",
      "size": 62621,
      "mtime": 1778587489.0345755,
      "mtime_iso": "2026-05-12T20:04:49"
    },
    {
      "relative_path": "C6对称结构\\六臂星\\results\\所有臂同步缩放扰动\\旧文件\\full\\不收敛\\run_full_2026年5月12日_20时01分04秒\\03_transmission_abs2_png\\0005_all_arm_length_arm_length_625.000nm_transmission_abs2.png",
      "name": "0005_all_arm_length_arm_length_625.000nm_transmission_abs2.png",
      "extension": "png",
      "kind": "image",
      "size": 65032,
      "mtime": 1778587535.624643,
      "mtime_iso": "2026-05-12T20:05:35"
    },
    {
      "relative_path": "C6对称结构\\六臂星\\results\\所有臂同步缩放扰动\\旧文件\\full\\不收敛\\run_full_2026年5月12日_20时01分04秒\\03_transmission_abs2_png\\0006_all_arm_length_arm_length_650.000nm_transmission_abs2.png",
      "name": "0006_all_arm_length_arm_length_650.000nm_transmission_abs2.png",
      "extension": "png",
      "kind": "image",
      "size": 64885,
      "mtime": 1778587580.3592858,
      "mtime_iso": "2026-05-12T20:06:20"
    },
    {
      "relative_path": "C6对称结构\\六臂星\\results\\所有臂同步缩放扰动\\旧文件\\full\\不收敛\\run_full_2026年5月12日_20时01分04秒\\03_transmission_abs2_png\\0007_all_arm_length_arm_length_675.000nm_transmission_abs2.png",
      "name": "0007_all_arm_length_arm_length_675.000nm_transmission_abs2.png",
      "extension": "png",
      "kind": "image",
      "size": 65018,
      "mtime": 1778587625.2814755,
      "mtime_iso": "2026-05-12T20:07:05"
    },
    {
      "relative_path": "C6对称结构\\六臂星\\results\\所有臂同步缩放扰动\\旧文件\\full\\不收敛\\run_full_2026年5月12日_20时01分04秒\\03_transmission_abs2_png\\0008_all_arm_length_arm_length_700.000nm_transmission_abs2.png",
      "name": "0008_all_arm_length_arm_length_700.000nm_transmission_abs2.png",
      "extension": "png",
      "kind": "image",
      "size": 64666,
      "mtime": 1778587673.02553,
      "mtime_iso": "2026-05-12T20:07:53"
    },
    {
      "relative_path": "C6对称结构\\六臂星\\results\\所有臂同步缩放扰动\\旧文件\\full\\不收敛\\run_full_2026年5月12日_20时01分04秒\\结构状态说明.md",
      "name": "结构状态说明.md",
      "extension": "md",
      "kind": "md",
      "size": 1099,
      "mtime": 1778587269.3476665,
      "mtime_iso": "2026-05-12T20:01:09"
    },
    {
      "relative_path": "C6对称结构\\六臂星\\results\\所有臂同步缩放扰动\\旧文件\\full\\不收敛\\run_full_2026年5月12日_20时01分04秒\\02_transmission_excel\\0000_all_arm_length_arm_length_500.000nm_transmission_abs2.xlsx",
      "name": "0000_all_arm_length_arm_length_500.000nm_transmission_abs2.xlsx",
      "extension": "xlsx",
      "kind": "xlsx",
      "size": 25448,
      "mtime": 1778587312.890365,
      "mtime_iso": "2026-05-12T20:01:52"
    },
    {
      "relative_path": "C6对称结构\\六臂星\\results\\所有臂同步缩放扰动\\旧文件\\full\\不收敛\\run_full_2026年5月12日_20时01分04秒\\02_transmission_excel\\0001_all_arm_length_arm_length_525.000nm_transmission_abs2.xlsx",
      "name": "0001_all_arm_length_arm_length_525.000nm_transmission_abs2.xlsx",
      "extension": "xlsx",
      "kind": "xlsx",
      "size": 25443,
      "mtime": 1778587356.7996182,
      "mtime_iso": "2026-05-12T20:02:36"
    },
    {
      "relative_path": "C6对称结构\\六臂星\\results\\所有臂同步缩放扰动\\旧文件\\full\\不收敛\\run_full_2026年5月12日_20时01分04秒\\02_transmission_excel\\0002_all_arm_length_arm_length_550.000nm_transmission_abs2.xlsx",
      "name": "0002_all_arm_length_arm_length_550.000nm_transmission_abs2.xlsx",
      "extension": "xlsx",
      "kind": "xlsx",
      "size": 25465,
      "mtime": 1778587401.521309,
      "mtime_iso": "2026-05-12T20:03:21"
    },
    {
      "relative_path": "C6对称结构\\六臂星\\results\\所有臂同步缩放扰动\\旧文件\\full\\不收敛\\run_full_2026年5月12日_20时01分04秒\\02_transmission_excel\\0003_all_arm_length_arm_length_575.000nm_transmission_abs2.xlsx",
      "name": "0003_all_arm_length_arm_length_575.000nm_transmission_abs2.xlsx",
      "extension": "xlsx",
      "kind": "xlsx",
      "size": 25462,
      "mtime": 1778587445.0585544,
      "mtime_iso": "2026-05-12T20:04:05"
    },
    {
      "relative_path": "C6对称结构\\六臂星\\results\\所有臂同步缩放扰动\\旧文件\\full\\不收敛\\run_full_2026年5月12日_20时01分04秒\\02_transmission_excel\\0004_all_arm_length_arm_length_600.000nm_transmission_abs2.xlsx",
      "name": "0004_all_arm_length_arm_length_600.000nm_transmission_abs2.xlsx",
      "extension": "xlsx",
      "kind": "xlsx",
      "size": 25487,
      "mtime": 1778587488.9072583,
      "mtime_iso": "2026-05-12T20:04:48"
    },
    {
      "relative_path": "C6对称结构\\六臂星\\results\\所有臂同步缩放扰动\\旧文件\\full\\不收敛\\run_full_2026年5月12日_20时01分04秒\\02_transmission_excel\\0005_all_arm_length_arm_length_625.000nm_transmission_abs2.xlsx",
      "name": "0005_all_arm_length_arm_length_625.000nm_transmission_abs2.xlsx",
      "extension": "xlsx",
      "kind": "xlsx",
      "size": 25510,
      "mtime": 1778587535.5026398,
      "mtime_iso": "2026-05-12T20:05:35"
    },
    {
      "relative_path": "C6对称结构\\六臂星\\results\\所有臂同步缩放扰动\\旧文件\\full\\不收敛\\run_full_2026年5月12日_20时01分04秒\\02_transmission_excel\\0006_all_arm_length_arm_length_650.000nm_transmission_abs2.xlsx",
      "name": "0006_all_arm_length_arm_length_650.000nm_transmission_abs2.xlsx",
      "extension": "xlsx",
      "kind": "xlsx",
      "size": 25578,
      "mtime": 1778587580.2256436,
      "mtime_iso": "2026-05-12T20:06:20"
    },
    {
      "relative_path": "C6对称结构\\六臂星\\results\\所有臂同步缩放扰动\\旧文件\\full\\不收敛\\run_full_2026年5月12日_20时01分04秒\\02_transmission_excel\\0007_all_arm_length_arm_length_675.000nm_transmission_abs2.xlsx",
      "name": "0007_all_arm_length_arm_length_675.000nm_transmission_abs2.xlsx",
      "extension": "xlsx",
      "kind": "xlsx",
      "size": 25506,
      "mtime": 1778587625.147915,
      "mtime_iso": "2026-05-12T20:07:05"
    },
    {
      "relative_path": "C6对称结构\\六臂星\\results\\所有臂同步缩放扰动\\旧文件\\full\\不收敛\\run_full_2026年5月12日_20时01分04秒\\02_transmission_excel\\0008_all_arm_length_arm_length_700.000nm_transmission_abs2.xlsx",
      "name": "0008_all_arm_length_arm_length_700.000nm_transmission_abs2.xlsx",
      "extension": "xlsx",
      "kind": "xlsx",
      "size": 25538,
      "mtime": 1778587672.8990602,
      "mtime_iso": "2026-05-12T20:07:52"
    }
  ],
  "metrics": [],
  "quality_flags": [
    "缺 R",
    "缺 A",
    "缺 Field",
    "缺 Phase",
    "缺 Poynting"
  ],
  "missing_evidence": [
    "R",
    "A",
    "Field",
    "Phase",
    "Poynting"
  ],
  "linked_supplements": [],
  "run_id": "run_full_2026年5月12日_20时01分04秒_96689add",
  "relative_path": "C6对称结构\\六臂星\\results\\所有臂同步缩放扰动\\旧文件\\full\\不收敛\\run_full_2026年5月12日_20时01分04秒",
  "group": "C6",
  "mother_structure": "六臂星",
  "perturbation": "所有臂同步缩放扰动",
  "reduction_path": "C6 -> 待识别",
  "status": "done",
  "risk": "medium",
  "risk_level": "medium",
  "risk_label": "中",
  "mode": "full",
  "spectrum_count": 10,
  "spectra_count": 10,
  "sample_count": 9,
  "has_T": true,
  "has_R": false,
  "has_A": false,
  "has_field": false,
  "has_phase": false,
  "has_poynting": false,
  "best_score": 4.635887189801226,
  "score": 4.635887189801226,
  "lambda0_nm": 1507.0921985815603,
  "Q": 5.01621290057215,
  "q": 5.01621290057215,
  "FWHM_nm": 300.44422524603397,
  "fwhm_nm": 300.44422524603397,
  "max_t": 0.9241807251310588,
  "modified_at": "2026-05-12T20:01:53",
  "mtime": 1778587313.4080186,
  "fingerprint": {
    "mtime_max": 1778587673.0265357,
    "total_size": 258840814,
    "file_count": 31,
    "dir_count": 6,
    "fingerprint": "1778587673.0265357-258840814-31-6"
  },
  "last_indexed_at": "2026-05-20T14:34:08",
  "source_job_id": null,
  "evidence": {
    "T": true,
    "R": false,
    "A": false,
    "Field": false,
    "Phase": false,
    "Poynting": false
  },
  "quality_flag_records": [
    {
      "run_id": "run_full_2026年5月12日_20时01分04秒_96689add",
      "sample_id": null,
      "flag": "缺 R",
      "severity": "warning",
      "detail": "缺少 R 补证数据",
      "suggestion": "进入补做实验生成任务包"
    },
    {
      "run_id": "run_full_2026年5月12日_20时01分04秒_96689add",
      "sample_id": null,
      "flag": "缺 A",
      "severity": "warning",
      "detail": "缺少 A 补证数据",
      "suggestion": "进入补做实验生成任务包"
    },
    {
      "run_id": "run_full_2026年5月12日_20时01分04秒_96689add",
      "sample_id": null,
      "flag": "缺 Field",
      "severity": "warning",
      "detail": "缺少 Field 补证数据",
      "suggestion": "进入补做实验生成任务包"
    },
    {
      "run_id": "run_full_2026年5月12日_20时01分04秒_96689add",
      "sample_id": null,
      "flag": "缺 Phase",
      "severity": "warning",
      "detail": "缺少 Phase 补证数据",
      "suggestion": "进入补做实验生成任务包"
    },
    {
      "run_id": "run_full_2026年5月12日_20时01分04秒_96689add",
      "sample_id": null,
      "flag": "缺 Poynting",
      "severity": "warning",
      "detail": "缺少 Poynting 补证数据",
      "suggestion": "进入补做实验生成任务包"
    }
  ]
}